{
  "type": "blog",
  "id": "blog-3",
  "slug": "blog-3",
  "title": "Üniversite Eğitimi İçin Almanya'yı Seçmenin 5 İyi Nedeni",
  "date": "2024-06-01 12:44:09",
  "seoTitle": "Almanya Vize Rehberi - Üniversite Eğitimi İçin Almanya'yı Seçmenin 5 İyi Nedeni",
  "seoDescription": "Almanya, yüksek öğrenim için dünya çapında giderek daha popüler bir destinasyon haline gelmiştir. Almanya'nın eğitim sistemi, güçlü ekonomisi ve kültürel zenginliği, her yıl binlerce uluslararası öğrenciyi cezbetmektedir. Almanya'da üniversite eğitimi almanın neden bu kadar cazip olduğunu merak ediyorsanız, işte size detaylı olarak açıklanmış beş iyi neden",
  "keywords": "Almanya vize rehberi, Almanya Üniversite Eğitimi, Almanya vizesi, Almanya çalışma vizesi, Almanya mavi kart, Almanya aile birleşimi, Almanya’da iş bulma, Almanya öğrenci vizesi, Almanya girişimci vizesi, Almanya araştırma vizesi",
  "canonical": "https://www.almanyavizerehberi.com//blog-yazi.php?l=3",
  "source": "/blog-yazi.php?l=3",
  "image": "https://2b.almanyavizerehberi.com/dist/img/blog/267163.jpg",
  "bodyHtml": "<p>Almanya, yüksek öğrenim için dünya çapında giderek daha popüler bir destinasyon haline gelmiştir. Almanya'nın eğitim sistemi, güçlü ekonomisi ve kültürel zenginliği, her yıl binlerce uluslararası öğrenciyi cezbetmektedir. Almanya'da üniversite eğitimi almanın neden bu kadar cazip olduğunu merak ediyorsanız, işte size detaylı olarak açıklanmış beş iyi neden:</p>\n\n<p>&nbsp;</p>\n\n<p><strong>1. Ücretsiz veya Düşük Maliyetli Eğitim</strong></p>\n\n<p>Almanya'da eğitim, çoğu devlet üniversitesinde ücretsizdir veya düşük öğrenim harçları ile sunulmaktadır. Almanya'nın bu politikası, özellikle Avrupa Birliği dışından gelen öğrenciler için bile geçerlidir. Eğitim maliyetlerinin düşük olması, öğrencilere kaliteli bir eğitim alma fırsatı sunarken, aynı zamanda finansal açıdan da büyük bir avantaj sağlar. Bu sayede, öğrenciler dünya çapında tanınan üniversitelerde yüksek kalitede eğitim alabilirken, aynı zamanda maliyetlerini de düşük tutabilirler.</p>\n\n<p>&nbsp;</p>\n\n<p>Almanya'nın eğitim sisteminde bu yaklaşım, eğitimin herkes için erişilebilir olmasını sağlar. Bunun sonucunda, Almanya’da okuyan uluslararası öğrenciler, mezun olduktan sonra büyük bir borç yükü altında kalmadan kariyerlerine başlayabilirler.</p>\n\n<p>&nbsp;</p>\n\n<p><strong>2. Yüksek Kaliteli Eğitim ve Araştırma Olanakları</strong></p>\n\n<p>Almanya, köklü bir eğitim geleneğine ve dünya çapında tanınan üniversitelere sahiptir. Almanya'daki üniversiteler, çeşitli akademik alanlarda sundukları kaliteli eğitimle tanınır. Bu üniversiteler, özellikle mühendislik, bilim, teknoloji, tıp ve sosyal bilimler alanlarında güçlü programlara sahiptir. Almanya’daki üniversitelerin birçoğu, dünya sıralamalarında üst sıralarda yer almakta ve uluslararası arenada prestijli bir konuma sahiptir.</p>\n\n<p>&nbsp;</p>\n\n<p>Almanya, araştırmaya verdiği önemle de bilinir. Almanya’da okuyan öğrenciler, dünyanın önde gelen araştırma kurumları ve laboratuvarlarında çalışma fırsatı bulabilirler. Ayrıca, üniversiteler ve endüstri arasındaki güçlü işbirliği, öğrencilere teorik bilgilerini pratik deneyimlerle birleştirme imkanı sunar.</p>\n\n<p>&nbsp;</p>\n\n<p><strong>3. Çeşitli Programlar ve İngilizce Eğitim İmkanları</strong></p>\n\n<p>Almanya’daki üniversiteler, çok çeşitli akademik programlar sunar. Öğrenciler, mühendislikten sosyal bilimlere, sanattan tıbba kadar geniş bir yelpazede programlar arasından seçim yapabilirler. Ayrıca, Almanya’da giderek artan sayıda üniversite, İngilizce olarak sunulan lisans ve yüksek lisans programları sunmaktadır. Bu, Almanca bilmeyen uluslararası öğrenciler için büyük bir avantajdır ve Almanya’da eğitim almak isteyen öğrencilerin dil bariyerini aşmalarını sağlar.</p>\n\n<p>&nbsp;</p>\n\n<p>Almanya'da İngilizce olarak sunulan programların sayısının artması, ülkeyi uluslararası öğrenciler için daha da cazip bir hale getiriyor. Ayrıca, Almanya'da eğitim gören öğrenciler, öğrenim süreleri boyunca Almanca öğrenme fırsatına da sahip olabilirler, bu da onların Almanya’da iş bulma ve topluma uyum sağlama şanslarını artırır.</p>\n\n<p>&nbsp;</p>\n\n<p><strong>4. Geniş Kariyer Fırsatları</strong></p>\n\n<p>Almanya, güçlü ve istikrarlı bir ekonomiye sahiptir ve mezunlara geniş kariyer fırsatları sunar. Özellikle mühendislik, bilişim teknolojileri, sağlık ve doğa bilimleri gibi alanlarda Almanya'da iş bulma şansı oldukça yüksektir. Almanya, nitelikli iş gücüne duyduğu ihtiyaç nedeniyle uluslararası öğrencilere çeşitli iş imkanları sunmaktadır. Mezun olduktan sonra, öğrenciler 18 aya kadar uzatılabilir bir iş arama vizesi alabilirler, bu da Almanya’da kalıp çalışmak isteyenler için büyük bir avantajdır.</p>\n\n<p>&nbsp;</p>\n\n<p>Almanya’da iş piyasası, mezunlara çeşitli kariyer yolları sunar ve bu sayede mezunlar, akademik bilgilerini uygulamalı olarak kullanabilecekleri alanlarda çalışma fırsatı bulurlar. Ayrıca, Almanya'daki birçok büyük şirket, uluslararası mezunları istihdam etmeye açıktır, bu da öğrencilerin global bir kariyere başlamalarına olanak tanır.</p>\n\n<p>&nbsp;</p>\n\n<p><strong>5. Kültürel Zenginlik ve Uluslararası Deneyim</strong></p>\n\n<p>Almanya, zengin bir kültürel mirasa ve çeşitli yaşam tarzlarına sahip bir ülkedir. Almanya’da eğitim gören öğrenciler, hem modern hem de geleneksel kültürün bir arada bulunduğu bir ortamda yaşama fırsatı bulurlar. Almanya’nın tarihi şehirleri, müzeleri, festivalleri ve doğal güzellikleri, öğrencilere keşfedilecek çok şey sunar. Almanya’nın Avrupa’nın merkezinde yer alması, öğrencilere çevre ülkeleri kolayca ziyaret etme fırsatı da sağlar.</p>\n\n<p>&nbsp;</p>\n\n<p>Almanya’daki üniversiteler, dünya çapında birçok ülkeden gelen öğrencilere ev sahipliği yapar. Bu, öğrencilerin uluslararası bir çevreye dahil olmalarını ve farklı kültürlerle etkileşimde bulunmalarını sağlar. Almanya’da eğitim görmek, öğrencilere sadece akademik gelişim değil, aynı zamanda kültürel ve sosyal anlamda da zenginleşme imkanı sunar.</p>\n\n<p>&nbsp;</p>\n\n<p>Sonuç olarak Almanya, üniversite eğitimi için mükemmel bir seçimdir. Ücretsiz veya düşük maliyetli eğitim, yüksek kaliteli akademik programlar, çeşitli İngilizce programlar, geniş kariyer fırsatları ve kültürel zenginlik, Almanya’yı üniversite eğitimi için cazip bir destinasyon haline getirir. Almanya’da üniversite eğitimi almak, hem kişisel hem de profesyonel anlamda size büyük avantajlar sunacaktır.</p>\n\n<p>&nbsp;</p>\n\n<p><strong>Kaynaklar:</strong></p>\n\n<p>&nbsp;</p>\n\n<p>Study in Germany : https://www.study-in-germany.de/de/</p>\n\n<p>DAAD (German Academic Exchange Service) : https://www.daad.de/en/</p>\n\n<p>Make it in Germany : <a href=\"https://www.make-it-in-germany.com/en/\">https://www.make-it-in-germany.com/en/</a></p>\n              <div class=\"read-more\">\n                <a href=\"blog.php\">Diğer Blog Yazıları</a>\n              </div>"
}